markdown_inline_graphviz.py
markdown_inline_graphviz_extension_png-1.1.dist-info/LICENSE
markdown_inline_graphviz_extension_png-1.1.dist-info/METADATA
markdown_inline_graphviz_extension_png-1.1.dist-info/WHEEL
markdown_inline_graphviz_extension_png-1.1.dist-info/top_level.txt
markdown_inline_graphviz_extension_png-1.1.dist-info/RECORD
